pyspeakercraft/__init__.py
pyspeakercraft-0.3.dist-info/METADATA
pyspeakercraft-0.3.dist-info/WHEEL
pyspeakercraft-0.3.dist-info/top_level.txt
pyspeakercraft-0.3.dist-info/RECORD
